{"Exif":{"Lat":0,"Long":0,"Date":"2025-08-26T21:40:29+01:00","Tags":{"ApertureValue":1.7962647457678684,"BrightnessValue":"undef","ComponentsConfiguration":"1 2 3 0","CreateDate":"2025:08:26 21:40:29","DateTimeOriginal":"2025:08:26 21:40:29","DigitalZoomRatio|*imagemeta.rat[uint32]":"21969/10000","ExposureCompensation|*imagemeta.rat[int32]":"0","ExposureTime|*imagemeta.rat[uint32]":"1/36","FNumber|*imagemeta.rat[uint32]":"9/5","FocalLengthIn35mmFormat|uint16":"77","FocalLength|*imagemeta.rat[uint32]":"758/125","ISO|uint16":"1250","ImageHeight|uint16":"4000","ImageWidth|uint16":"3008","LensModel":"OnePlus 10 Pro 5G back camera 6.06mm f/1.8","Make":"OnePlus","MakerNoteApple":"{\"PiFlag\":\"0\",\"nightFlag\":\"0\",\"nightMode\": \"0\",\"asdOut\": [\"0\"],\"apsAsdOut\": [\"0\"],\"apsAsdClsOut\": [\"0\", \"0\"],\"iso\": \"2130\",\"expTime\": \"0\",\"fType\":\"6\",\"bkMode\":\"1\",\"aideblur\":\"0\",\"aisState\":\"0\"}","MaxApertureValue":1.7962647457678684,"Model":"OnePlus 10 Pro 5G","ModifyDate":"2025:08:26 21:40:29","OffsetTimeOriginal":"+01:00","Orientation|uint16":"1","SceneCaptureType|uint16":"0","SceneType|uint8":"0","ShutterSpeedValue":0.0280083343615439,"SubSecTimeDigitized|int":"368","SubSecTimeOriginal|int":"368","SubSecTime|int":"368","UserComment":"","YCbCrPositioning|uint16":"1"}}}
